[{"name":"Yashasvi Jaiswal ","fallOfWicket":"c & b Chahar","Run":"6","Ball":"6","Four":"1","Six":"0","SR":"100.00"},{"name":"Steven Smith (c)","fallOfWicket":"c Jadhav b Curran","Run":"69","Ball":"47","Four":"4","Six":"4","SR":"146.80"},{"name":"Sanju Samson †","fallOfWicket":"c Chahar b Ngidi","Run":"74","Ball":"32","Four":"1","Six":"9","SR":"231.25"},{"name":"David Miller ","fallOfWicket":"run out (Gaikwad/Jadhav)","Run":"0","Ball":"0","Four":"0","Six":"0","SR":"-"},{"name":"Robin Uthappa ","fallOfWicket":"c du Plessis b Chawla","Run":"5","Ball":"9","Four":"0","Six":"0","SR":"55.55"},{"name":"Rahul Tewatia ","fallOfWicket":"lbw b Curran","Run":"10","Ball":"8","Four":"1","Six":"0","SR":"125.00"},{"name":"Riyan Parag ","fallOfWicket":"c †Dhoni b Curran","Run":"6","Ball":"4","Four":"1","Six":"0","SR":"150.00"},{"name":"Tom Curran ","fallOfWicket":"not out ","Run":"10","Ball":"9","Four":"1","Six":"0","SR":"111.11"},{"name":"Jofra Archer ","fallOfWicket":"not out ","Run":"27","Ball":"8","Four":"0","Six":"4","SR":"337.50"},{"Extras":"(b 1, nb 3, w 5) 9"},{"Total":"216/7   (20 Ov, RR: 10.80)"}]